{
  "results": [
  {
  "name": "AMORE FLOREALS MOCK",
  "slug": "amore-florals",
  "uuid": "0bc1618f-afab-4117-803e-b7cf83517917",
  "tags": [
  {
  "pid": "15",
  "name": "Bridal Bouquets",
  "tagId": "a30ee396-fd2b-4987-ae55-d0533fa3a035"
  },
  {
  "pid": "15",
  "name": "Table Arrangements",
  "tagId": "16d2be56-e34d-45a6-afbb-6031e19194e8"
  },
  {
  "pid": "15",
  "name": "Venue Arrangements",
  "tagId": "356d43b8-89ac-48e2-b171-d50736fe29a2"
  },
  {
  "pid": "15",
  "name": "Bridesmaids/Groomsmen flowers",
  "tagId": "e1b60866-1e84-4005-a284-5979e4935e54"
  },
  {
  "pid": "15",
  "name": "Floral Baskets",
  "tagId": "4780f591-15a0-44a4-97ea-052936dbae47"
  },
  {
  "pid": "15",
  "name": "Standing Sprays",
  "tagId": "896d95a6-1cc8-4c88-9724-35e9ecdd527c"
  },
  {
  "pid": "15",
  "name": "Installations",
  "tagId": "d3174ae6-410f-446a-a283-138d57a2f2fa"
  },
  {
  "pid": "15",
  "name": "Wreaths",
  "tagId": "6b40b393-7121-471e-92c7-11850792bae6"
  },
  {
  "pid": "10",
  "name": "Luxury Florist",
  "tagId": "x5dUjh2Um"
  }
  ],
  "tier2": [
  {
  "name": "Florists",
  "sysName": "florists"
  }
  ],
  "state": "active",
  "updated": "2020-07-15T11:35:19.499Z",
  "trusted": false,
  "visible": true,
  "dietary": [],
  "categoryTier1": "florists",
  "public": {
  "images": [
  {
  "id": "JWFswEo9a",
  "eid": "0bc1618f-afab-4117-803e-b7cf83517917",
  "url": "https://feast-it-web-prod.imgix.net/0bc1618f-afab-4117-803e-b7cf83517917/JWFswEo9a/FB_IMG_1593342138577.jpg",
  "title": ""
  },
  {
  "id": "d7e8Q3oED",
  "eid": "0bc1618f-afab-4117-803e-b7cf83517917",
  "url": "https://feast-it-web-prod.imgix.net/0bc1618f-afab-4117-803e-b7cf83517917/d7e8Q3oED/FB_IMG_1590252850320.jpg",
  "title": ""
  },
  {
  "id": "nL42kdQK9",
  "eid": "0bc1618f-afab-4117-803e-b7cf83517917",
  "url": "https://feast-it-web-prod.imgix.net/0bc1618f-afab-4117-803e-b7cf83517917/nL42kdQK9/FB_IMG_1593342193983.jpg",
  "title": ""
  },
  {
  "id": "MDMLkHW3I",
  "eid": "0bc1618f-afab-4117-803e-b7cf83517917",
  "url": "https://feast-it-web-prod.imgix.net/0bc1618f-afab-4117-803e-b7cf83517917/MDMLkHW3I/FB_IMG_1590252847544.jpg",
  "title": ""
  },
  {
  "id": "1L4FLk1EN",
  "eid": "0bc1618f-afab-4117-803e-b7cf83517917",
  "url": "https://feast-it-web-prod.imgix.net/0bc1618f-afab-4117-803e-b7cf83517917/1L4FLk1EN/FB_IMG_1590694836881.jpg",
  "title": ""
  },
  {
  "id": "8m0KB9qG5",
  "eid": "0bc1618f-afab-4117-803e-b7cf83517917",
  "url": "https://feast-it-web-prod.imgix.net/0bc1618f-afab-4117-803e-b7cf83517917/8m0KB9qG5/FB_IMG_1593257654945.jpg",
  "title": ""
  }
  ],
  "social": [],
  "basePrice": 10,
  "video_url": null,
  "commission": 17.5,
  "description": "<p>Amore Florals, based in Leighton Buzzard, was founded in 2019 by the wonderful Miranda. With over ten years floristry experience under her belt, including time working for world-famous florist, Paula Pryke, Miranda's stunning floral designs speak for themselves.</p><p>Amore Florals believe that wedding flowers play a significant part in creating the atmosphere on the day and are guaranteed to make your big day one to remember! If you're organising a corporate event, their team can create floral designs to make sure you leave a lasting impression on your guests.</p><p>With experience working for some of London's most prestigious luxury events and celebrity weddings, Amore Florals are the perfect pick for your event. Book them here on Feast It!</p>",
  "profilePicture": {
  "id": "t32x7GFsO",
  "eid": "0bc1618f-afab-4117-803e-b7cf83517917",
  "url": "https://feast-it-web-prod.imgix.net/0bc1618f-afab-4117-803e-b7cf83517917/t32x7GFsO/FB_IMG_1591172563649.jpg",
  "title": ""
  },
  "logistics": {
  "radius": 80000,
  "minSpend": 500,
  "VATNumber": null,
  "setup": {
  "power": null,
  "water": null,
  "details": null
  },
  "location": {
  "lat": 51.921245,
  "long": -0.679043
  },
  "VATRegistered": false,
  "registeredName": null,
  "maxWorkingHours": 12,
  "registeredAddress": {
  "city": "",
  "line1": "",
  "line2": "",
  "postcode": ""
  },
  "availableHours": {
  "end": "22:00",
  "start": "06:00"
  },
  "companyRegistrationNumber": null
  }
  },
  "categoryFields": {},
  "external": {
  "numReviews": "0",
  "hygieneRating": null,
  "rating": {
  "overall": "0.0",
  "quality": null,
  "friendliness": null,
  "valueForMoney": null,
  "professionalism": null
  },
  "iZettleStaffName": null,
  "foodSafetyAgencyId": null
  },
  "algorithmDiscoverable": true
  },
  {
  "name": "Grace and Thorn ",
  "slug": "grace-and-thorn-florist",
  "uuid": "1e65b06c-1bbf-45ad-babf-74c479c045c7",
  "tags": [
  {
  "pid": "15",
  "name": "Bridal Bouquets",
  "tagId": "a30ee396-fd2b-4987-ae55-d0533fa3a035"
  },
  {
  "pid": "15",
  "name": "Table Arrangements",
  "tagId": "16d2be56-e34d-45a6-afbb-6031e19194e8"
  },
  {
  "pid": "15",
  "name": "Venue Arrangements",
  "tagId": "356d43b8-89ac-48e2-b171-d50736fe29a2"
  },
  {
  "pid": "15",
  "name": "Bridesmaids/Groomsmen flowers",
  "tagId": "e1b60866-1e84-4005-a284-5979e4935e54"
  },
  {
  "pid": "15",
  "name": "Floral Baskets",
  "tagId": "4780f591-15a0-44a4-97ea-052936dbae47"
  },
  {
  "pid": "15",
  "name": "Standing Sprays",
  "tagId": "896d95a6-1cc8-4c88-9724-35e9ecdd527c"
  },
  {
  "pid": "15",
  "name": "Installations",
  "tagId": "d3174ae6-410f-446a-a283-138d57a2f2fa"
  },
  {
  "pid": "15",
  "name": "Wreaths",
  "tagId": "6b40b393-7121-471e-92c7-11850792bae6"
  },
  {
  "pid": "10",
  "name": "Elegant Plants & Flowers",
  "tagId": "1m9Mv7h4m"
  }
  ],
  "tier2": [
  {
  "name": "Florists",
  "sysName": "florists"
  }
  ],
  "state": "active",
  "updated": "2020-08-05T08:32:21.512Z",
  "trusted": false,
  "visible": true,
  "dietary": [],
  "categoryTier1": "florists",
  "public": {
  "images": [
  {
  "id": "0mYijTEp8",
  "eid": "1e65b06c-1bbf-45ad-babf-74c479c045c7",
  "url": "https://feast-it-web-prod.imgix.net/1e65b06c-1bbf-45ad-babf-74c479c045c7/0mYijTEp8/Screen%20Shot%202020-07-13%20at%2010.36.38.png",
  "title": ""
  },
  {
  "id": "E6eUBKe-W",
  "eid": "1e65b06c-1bbf-45ad-babf-74c479c045c7",
  "url": "https://feast-it-web-prod.imgix.net/1e65b06c-1bbf-45ad-babf-74c479c045c7/E6eUBKe-W/Feast-It-Grace-Thorn-Hackney-Florist6.jpeg",
  "title": ""
  },
  {
  "id": "pN9Pml2J6E",
  "eid": "1e65b06c-1bbf-45ad-babf-74c479c045c7",
  "url": "https://feast-it-web-prod.imgix.net/1e65b06c-1bbf-45ad-babf-74c479c045c7/pN9Pml2J6E/Screen_Shot_2020_07_07_at_15.51.45.JPG",
  "title": ""
  },
  {
  "id": "1hi1IaiLND",
  "eid": "1e65b06c-1bbf-45ad-babf-74c479c045c7",
  "url": "https://feast-it-web-prod.imgix.net/1e65b06c-1bbf-45ad-babf-74c479c045c7/1hi1IaiLND/Feast-It-Grace-Thorn-Hackney-Florist3.jpg",
  "title": ""
  },
  {
  "id": "oiqw6bTel",
  "eid": "1e65b06c-1bbf-45ad-babf-74c479c045c7",
  "url": "https://feast-it-web-prod.imgix.net/1e65b06c-1bbf-45ad-babf-74c479c045c7/oiqw6bTel/Kate_and_Stephens_Wedding-236_800x.jpg",
  "title": ""
  },
  {
  "id": "uzwF3L_ZnE",
  "eid": "1e65b06c-1bbf-45ad-babf-74c479c045c7",
  "url": "https://feast-it-web-prod.imgix.net/1e65b06c-1bbf-45ad-babf-74c479c045c7/uzwF3L_ZnE/Feast-It-Grace-Thorn-Hackney-Florist5.jpg",
  "title": ""
  },
  {
  "id": "GVMb5bL_oA",
  "eid": "1e65b06c-1bbf-45ad-babf-74c479c045c7",
  "url": "https://feast-it-web-prod.imgix.net/1e65b06c-1bbf-45ad-babf-74c479c045c7/GVMb5bL_oA/Feast-It-Grace-Thorn-Hackney-Florist1.jpg",
  "title": ""
  },
  {
  "id": "-64pJQQ_q",
  "eid": "1e65b06c-1bbf-45ad-babf-74c479c045c7",
  "url": "https://feast-it-web-prod.imgix.net/1e65b06c-1bbf-45ad-babf-74c479c045c7/-64pJQQ_q/Screen_Shot_2020_07_07_at_15.37.51.JPG",
  "title": ""
  },
  {
  "id": "wBbDo2M2Xu",
  "eid": "1e65b06c-1bbf-45ad-babf-74c479c045c7",
  "url": "https://feast-it-web-prod.imgix.net/1e65b06c-1bbf-45ad-babf-74c479c045c7/wBbDo2M2Xu/Screen_Shot_2020_07_07_at_15.37.08.JPG",
  "title": ""
  },
  {
  "id": "CcivQ13Y4",
  "eid": "1e65b06c-1bbf-45ad-babf-74c479c045c7",
  "url": "https://feast-it-web-prod.imgix.net/1e65b06c-1bbf-45ad-babf-74c479c045c7/CcivQ13Y4/Screen_Shot_2020_07_07_at_15.46.11.JPG",
  "title": ""
  },
  {
  "id": "WRTrnwGDb4",
  "eid": "1e65b06c-1bbf-45ad-babf-74c479c045c7",
  "url": "https://feast-it-web-prod.imgix.net/1e65b06c-1bbf-45ad-babf-74c479c045c7/WRTrnwGDb4/Screen_Shot_2020_07_07_at_15.38.14.JPG",
  "title": ""
  },
  {
  "id": "NjXRnmIMc",
  "eid": "1e65b06c-1bbf-45ad-babf-74c479c045c7",
  "url": "https://feast-it-web-prod.imgix.net/1e65b06c-1bbf-45ad-babf-74c479c045c7/NjXRnmIMc/Screen_Shot_2020_07_07_at_16.08.46.JPG",
  "title": ""
  },
  {
  "id": "YFHA3AYy-",
  "eid": "1e65b06c-1bbf-45ad-babf-74c479c045c7",
  "url": "https://feast-it-web-prod.imgix.net/1e65b06c-1bbf-45ad-babf-74c479c045c7/YFHA3AYy-/Feast-It-Grace-Thorn-Hackney-Florist2.jpg",
  "title": ""
  },
  {
  "id": "8DMjj0gOk",
  "eid": "1e65b06c-1bbf-45ad-babf-74c479c045c7",
  "url": "https://feast-it-web-prod.imgix.net/1e65b06c-1bbf-45ad-babf-74c479c045c7/8DMjj0gOk/Screen%20Shot%202020-07-13%20at%2010.37.11.png",
  "title": ""
  }
  ],
  "social": [],
  "basePrice": 10,
  "video_url": null,
  "commission": 17.5,
  "description": "<p>Grace and Thorn is a rule-breaking florist renowned for their off-beat approach to floral and plant styling. Founded in 2011 by Nikola Southern, with the ethos that no two should ever be the same, their floral arrangements are sure to make a statement at any event.&nbsp;</p><p>Grace have a extensive experience in both floral and plant design, and come armed with a plethora of vases, pots and props options for you to choose from.&nbsp;</p><p>Whatever the brief, Grace and Thorn can offer small and large scale events service, weddings flowers, online and in-store bespoke bouquets and workshops too.</p><p>With regular mentions in the press, including being named top florist in London, best bouquet alongside Nikola Southern and being featured in numerous publications you can be confident that Grace and Thorn will deliver nothing but pure excellence.&nbsp;</p><p>Book them on Feast It today!</p>",
  "profilePicture": {
  "id": "tj_AQGj7N",
  "eid": "1e65b06c-1bbf-45ad-babf-74c479c045c7",
  "url": "https://feast-it-web-prod.imgix.net/1e65b06c-1bbf-45ad-babf-74c479c045c7/tj_AQGj7N/Screen_Shot_2020_07_07_at_15.35.05.JPG",
  "title": ""
  },
  "logistics": {
  "radius": 250000,
  "minSpend": 500,
  "VATNumber": "193323018",
  "setup": {
  "power": null,
  "water": null,
  "details": null
  },
  "location": {
  "lat": 51.508084,
  "long": -0.009933
  },
  "VATRegistered": true,
  "registeredName": null,
  "maxWorkingHours": 12,
  "registeredAddress": {
  "city": "London",
  "line1": "312 Hackney Road",
  "line2": "",
  "postcode": "E2 7SJ"
  },
  "availableHours": {
  "end": "24:00",
  "start": "06:00"
  },
  "companyRegistrationNumber": null
  }
  },
  "categoryFields": {},
  "external": {
  "numReviews": "0",
  "hygieneRating": null,
  "rating": {
  "overall": "0.0",
  "quality": null,
  "friendliness": null,
  "valueForMoney": null,
  "professionalism": null
  },
  "iZettleStaffName": null,
  "foodSafetyAgencyId": null
  },
  "algorithmDiscoverable": true
  },
  {
  "name": "Edie Rose ",
  "slug": "edie-rose-florist",
  "uuid": "238facc4-6661-4a87-9187-c10dbfd775ff",
  "tags": [
  {
  "pid": "10",
  "name": "Wedding & Event Florist",
  "tagId": "e7bCE_YE3"
  }
  ],
  "tier2": [
  {
  "name": "Florists",
  "sysName": "florists"
  }
  ],
  "state": "active",
  "updated": "2020-09-11T10:38:25.845Z",
  "trusted": false,
  "visible": true,
  "dietary": [],
  "categoryTier1": "florists",
  "public": {
  "images": [
  {
  "id": "EVmu_spmP",
  "eid": "238facc4-6661-4a87-9187-c10dbfd775ff",
  "url": "https://feast-it-web-prod.imgix.net/238facc4-6661-4a87-9187-c10dbfd775ff/EVmu_spmP/Feast_it_Edie_Rose.DSC_0194.JPG",
  "title": ""
  },
  {
  "id": "X9IRCFLcWD",
  "eid": "238facc4-6661-4a87-9187-c10dbfd775ff",
  "url": "https://feast-it-web-prod.imgix.net/238facc4-6661-4a87-9187-c10dbfd775ff/X9IRCFLcWD/Feast_it_Edie_Rose.DSC_0220.JPG",
  "title": ""
  },
  {
  "id": "08J4DBT_s",
  "eid": "238facc4-6661-4a87-9187-c10dbfd775ff",
  "url": "https://feast-it-web-prod.imgix.net/238facc4-6661-4a87-9187-c10dbfd775ff/08J4DBT_s/Feast_it_Edie_Rose.DSC_0194%20(1).JPG",
  "title": ""
  },
  {
  "id": "OLf5jFdxPf",
  "eid": "238facc4-6661-4a87-9187-c10dbfd775ff",
  "url": "https://feast-it-web-prod.imgix.net/238facc4-6661-4a87-9187-c10dbfd775ff/OLf5jFdxPf/Feast_it_Edie_Rose.DSC_0106.JPG",
  "title": ""
  },
  {
  "id": "d0ZRBBPPXu",
  "eid": "238facc4-6661-4a87-9187-c10dbfd775ff",
  "url": "https://feast-it-web-prod.imgix.net/238facc4-6661-4a87-9187-c10dbfd775ff/d0ZRBBPPXu/Feast_it_Edie_Rose.DSC_0253.JPG",
  "title": ""
  },
  {
  "id": "_ZUkLZqRbD",
  "eid": "238facc4-6661-4a87-9187-c10dbfd775ff",
  "url": "https://feast-it-web-prod.imgix.net/238facc4-6661-4a87-9187-c10dbfd775ff/_ZUkLZqRbD/Feast_it_Edie_Rose.E568DE37_95BA_45BF_A8D2_C273EB5A0902.jpeg",
  "title": ""
  },
  {
  "id": "zKHTxuqe7r",
  "eid": "238facc4-6661-4a87-9187-c10dbfd775ff",
  "url": "https://feast-it-web-prod.imgix.net/238facc4-6661-4a87-9187-c10dbfd775ff/zKHTxuqe7r/Feast_it_Edie_Rose.DSC_0334.JPG",
  "title": ""
  }
  ],
  "social": [],
  "basePrice": 10,
  "video_url": null,
  "commission": 17.5,
  "description": "<p>The Edie rose style is natural &amp; off-beat with a strong focus on creating stunning floral displays which are wild and free. Colours &amp; textures which delight the eye play an important part in their style. They work with fresh, dried, preserved or faux flowers &amp; foliage creating beautiful floral designs using seasonal flowers</p><p>From vision to completion, they offer their technical know how and work alongside you to achieve outstanding designs. With each brief they consider fresh sustainable ideas which will suit each individual client. Edie Rose strives to be as eco-friendly as possible and look for fresh innovative ways to make a difference in the industry.</p><p>Edie Rose started in 2015, when founder Helen wanted to produce beautiful floral designs which made the heart smile. They first started delivering bouquets remotely and gradually building their client base.&nbsp;</p><p>Soon, they grew in size and opened 3 more shops in London to look after the day to day offerings. They then moved into the wedding and events space and started with large scale event, venues, brands &amp; event teams across the UK.&nbsp;</p>",
  "profilePicture": {
  "id": "OZLr0fMbe",
  "eid": "238facc4-6661-4a87-9187-c10dbfd775ff",
  "url": "https://feast-it-web-prod.imgix.net/238facc4-6661-4a87-9187-c10dbfd775ff/OZLr0fMbe/Feast_it_Edie_Rose.DSC_0334.JPG",
  "title": ""
  },
  "logistics": {
  "radius": 25000,
  "minSpend": 500,
  "VATNumber": "285444086",
  "setup": {
  "power": null,
  "water": null,
  "details": null
  },
  "location": {
  "lat": 51.56421,
  "long": -0.006763
  },
  "VATRegistered": true,
  "registeredName": null,
  "maxWorkingHours": 12,
  "registeredAddress": {
  "city": "London",
  "line1": "228 Francis Road",
  "line2": "",
  "postcode": "E11 4DS"
  },
  "availableHours": {
  "end": "24:00",
  "start": "06:00"
  },
  "companyRegistrationNumber": null
  }
  },
  "categoryFields": {},
  "external": {
  "numReviews": "0",
  "hygieneRating": null,
  "rating": {
  "overall": "0.0",
  "quality": null,
  "friendliness": null,
  "valueForMoney": null,
  "professionalism": null
  },
  "iZettleStaffName": null,
  "foodSafetyAgencyId": null
  },
  "algorithmDiscoverable": true
  },
  {
  "name": "Philipa Day ",
  "slug": "philipa-day-florist",
  "uuid": "2453578f-136c-428a-9b5e-e312f4ad6b96",
  "tags": [
  {
  "pid": "15",
  "name": "Bridal Bouquets",
  "tagId": "a30ee396-fd2b-4987-ae55-d0533fa3a035"
  },
  {
  "pid": "15",
  "name": "Table Arrangements",
  "tagId": "16d2be56-e34d-45a6-afbb-6031e19194e8"
  },
  {
  "pid": "15",
  "name": "Venue Arrangements",
  "tagId": "356d43b8-89ac-48e2-b171-d50736fe29a2"
  },
  {
  "pid": "15",
  "name": "Bridesmaids/Groomsmen flowers",
  "tagId": "e1b60866-1e84-4005-a284-5979e4935e54"
  },
  {
  "pid": "15",
  "name": "Floral Baskets",
  "tagId": "4780f591-15a0-44a4-97ea-052936dbae47"
  },
  {
  "pid": "15",
  "name": "Standing Sprays",
  "tagId": "896d95a6-1cc8-4c88-9724-35e9ecdd527c"
  },
  {
  "pid": "15",
  "name": "Installations",
  "tagId": "d3174ae6-410f-446a-a283-138d57a2f2fa"
  },
  {
  "pid": "15",
  "name": "Wreaths",
  "tagId": "6b40b393-7121-471e-92c7-11850792bae6"
  },
  {
  "pid": "10",
  "name": "Independent Florist",
  "tagId": "u_sElFgLL"
  }
  ],
  "tier2": [
  {
  "name": "Florists",
  "sysName": "florists"
  }
  ],
  "state": "active",
  "updated": "2020-07-24T13:36:24.683Z",
  "trusted": false,
  "visible": true,
  "dietary": [],
  "categoryTier1": "florists",
  "public": {
  "images": [
  {
  "id": "F1Idw4YeQ",
  "eid": "2453578f-136c-428a-9b5e-e312f4ad6b96",
  "url": "https://feast-it-web-prod.imgix.net/2453578f-136c-428a-9b5e-e312f4ad6b96/F1Idw4YeQ/Philipa_day.Philipa_day.13F28F9E-17A9-4B9E-B11C-3AA33B3FA622.jpeg",
  "title": ""
  },
  {
  "id": "sCNc1WoFp",
  "eid": "2453578f-136c-428a-9b5e-e312f4ad6b96",
  "url": "https://feast-it-web-prod.imgix.net/2453578f-136c-428a-9b5e-e312f4ad6b96/sCNc1WoFp/Philipa_day.A2915CC9-EEE4-4A5A-9C1B-5E727AE05334.jpeg",
  "title": ""
  },
  {
  "id": "XV-gtWdPb",
  "eid": "2453578f-136c-428a-9b5e-e312f4ad6b96",
  "url": "https://feast-it-web-prod.imgix.net/2453578f-136c-428a-9b5e-e312f4ad6b96/XV-gtWdPb/Philipa_day.87134677_10221689247120982_7361917096051081216_n.jpg",
  "title": ""
  },
  {
  "id": "ecRc6DBRg",
  "eid": "2453578f-136c-428a-9b5e-e312f4ad6b96",
  "url": "https://feast-it-web-prod.imgix.net/2453578f-136c-428a-9b5e-e312f4ad6b96/ecRc6DBRg/Feast_It_%20Philipa%20DayScreen%20Shot%202020-07-08%20at%2015.13.19.png",
  "title": ""
  },
  {
  "id": "Xd72MgEYj",
  "eid": "2453578f-136c-428a-9b5e-e312f4ad6b96",
  "url": "https://feast-it-web-prod.imgix.net/2453578f-136c-428a-9b5e-e312f4ad6b96/Xd72MgEYj/Gallery_Images_2_Philipa%20Day.JPG",
  "title": ""
  },
  {
  "id": "mcY8pMEE5",
  "eid": "2453578f-136c-428a-9b5e-e312f4ad6b96",
  "url": "https://feast-it-web-prod.imgix.net/2453578f-136c-428a-9b5e-e312f4ad6b96/mcY8pMEE5/Philipa_day.F5F65E59-3E60-4DDE-9E85-6D03F7491C5B.jpeg",
  "title": ""
  },
  {
  "id": "f7ixIIRwz",
  "eid": "2453578f-136c-428a-9b5e-e312f4ad6b96",
  "url": "https://feast-it-web-prod.imgix.net/2453578f-136c-428a-9b5e-e312f4ad6b96/f7ixIIRwz/Philipa_day.Philipa_day.76959846-72C9-4E91-90D2-62E05CBA812C.jpeg",
  "title": ""
  },
  {
  "id": "Ah_1-ZsMf",
  "eid": "2453578f-136c-428a-9b5e-e312f4ad6b96",
  "url": "https://feast-it-web-prod.imgix.net/2453578f-136c-428a-9b5e-e312f4ad6b96/Ah_1-ZsMf/Philipa_day.IMG_0983.jpg",
  "title": ""
  },
  {
  "id": "mY8A8uurcx",
  "eid": "2453578f-136c-428a-9b5e-e312f4ad6b96",
  "url": "https://feast-it-web-prod.imgix.net/2453578f-136c-428a-9b5e-e312f4ad6b96/mY8A8uurcx/Philipa_day.DC98D50C-E5E2-464B-8B2D-75436480C71A.jpg",
  "title": ""
  },
  {
  "id": "NFPq48hsU",
  "eid": "2453578f-136c-428a-9b5e-e312f4ad6b96",
  "url": "https://feast-it-web-prod.imgix.net/2453578f-136c-428a-9b5e-e312f4ad6b96/NFPq48hsU/Philipa_day.66EDBD3F-54D4-4E99-A331-65296C81D424.jpg",
  "title": ""
  },
  {
  "id": "o27OjRe_3",
  "eid": "2453578f-136c-428a-9b5e-e312f4ad6b96",
  "url": "https://feast-it-web-prod.imgix.net/2453578f-136c-428a-9b5e-e312f4ad6b96/o27OjRe_3/Feast_It_%20Philipa%20DayScreen%20Shot%202020-07-08%20at%2015.14.15.png",
  "title": ""
  },
  {
  "id": "wVj6D_3kZ",
  "eid": "2453578f-136c-428a-9b5e-e312f4ad6b96",
  "url": "https://feast-it-web-prod.imgix.net/2453578f-136c-428a-9b5e-e312f4ad6b96/wVj6D_3kZ/Feast_It_%20Philipa_Day_2020-07-08%20at%2015.12.59.png",
  "title": ""
  },
  {
  "id": "w_MakdTH_t",
  "eid": "2453578f-136c-428a-9b5e-e312f4ad6b96",
  "url": "https://feast-it-web-prod.imgix.net/2453578f-136c-428a-9b5e-e312f4ad6b96/w_MakdTH_t/Gallery_Images_3_Philipa%20Day.jpg",
  "title": ""
  },
  {
  "id": "uo4u6gci0",
  "eid": "2453578f-136c-428a-9b5e-e312f4ad6b96",
  "url": "https://feast-it-web-prod.imgix.net/2453578f-136c-428a-9b5e-e312f4ad6b96/uo4u6gci0/Gallery_Images_Philipa%20Day.jpg",
  "title": ""
  },
  {
  "id": "GDl7KaUjh",
  "eid": "2453578f-136c-428a-9b5e-e312f4ad6b96",
  "url": "https://feast-it-web-prod.imgix.net/2453578f-136c-428a-9b5e-e312f4ad6b96/GDl7KaUjh/philipa%20day%201.jpg",
  "title": ""
  },
  {
  "id": "vTLk-WdcR",
  "eid": "2453578f-136c-428a-9b5e-e312f4ad6b96",
  "url": "https://feast-it-web-prod.imgix.net/2453578f-136c-428a-9b5e-e312f4ad6b96/vTLk-WdcR/philipa%20day.jpg",
  "title": ""
  },
  {
  "id": "jA9zspd77",
  "eid": "2453578f-136c-428a-9b5e-e312f4ad6b96",
  "url": "https://feast-it-web-prod.imgix.net/2453578f-136c-428a-9b5e-e312f4ad6b96/jA9zspd77/Philipa_day.Philipa_day.26E51F3A-AAA1-4225-8E0E-70333FEBA328.jpeg",
  "title": ""
  }
  ],
  "social": [],
  "basePrice": 10,
  "video_url": null,
  "commission": 17.5,
  "description": "<p>I studied Fine Art at Lancaster University, before aspiring to abstract art for a brief time. Soon after I realised my love for flowers which led me to retrain and start my own business as an independent florist.</p><p>As a former abstract painter, my style is driven by my love for colour and composition. For me, the apogee of this can be found in an English garden, which inspires my work.</p><p>My designs harness a close eye for detail, a respect for the natural world and an appreciation of the aesthetic. From a studio space on the border of Essex and East London, I provided exquisite, elegant and romantic flowers for weddings, events, homes and businesses across the UK.</p><p>In homage to all things sustainable, I've been growing my own blooms. My cutting garden is used in tandem with seasonal flowers sourced from England’s best flower markets and local growers. In each design my aim is for you to feel my love affair with nature, the flowers provided have been tended to, hand-grown, and handpicked just for you.</p>",
  "profilePicture": {
  "id": "ZwDpRAgQe",
  "eid": "2453578f-136c-428a-9b5e-e312f4ad6b96",
  "url": "https://feast-it-web-prod.imgix.net/2453578f-136c-428a-9b5e-e312f4ad6b96/ZwDpRAgQe/IMG_0827_2.JPG",
  "title": ""
  },
  "logistics": {
  "radius": 50000,
  "minSpend": 250,
  "VATNumber": null,
  "setup": {
  "power": null,
  "water": null,
  "details": "<p><br></p>"
  },
  "location": {
  "lat": 51.606468,
  "long": 0.052957
  },
  "VATRegistered": false,
  "registeredName": null,
  "maxWorkingHours": 12,
  "registeredAddress": {
  "city": "London",
  "line1": "22 Gainsborough Road",
  "line2": "Woodford Green",
  "postcode": "IG8 8EE"
  },
  "availableHours": {
  "end": "24:00",
  "start": "06:00"
  },
  "companyRegistrationNumber": null
  }
  },
  "categoryFields": {},
  "external": {
  "numReviews": "7",
  "hygieneRating": null,
  "rating": {
  "overall": "5.0",
  "quality": "5.0",
  "friendliness": "5.0",
  "valueForMoney": "5.0",
  "professionalism": "5.0"
  },
  "iZettleStaffName": null,
  "foodSafetyAgencyId": null
  },
  "algorithmDiscoverable": true
  },
  {
  "name": "Sweet Pea Rosa",
  "slug": "sweet-pea-rosa",
  "uuid": "2b8ac67c-611e-46ac-b944-b406f2fc89c3",
  "tags": [
  {
  "pid": "15",
  "name": "Bridal Bouquets",
  "tagId": "a30ee396-fd2b-4987-ae55-d0533fa3a035"
  },
  {
  "pid": "15",
  "name": "Table Arrangements",
  "tagId": "16d2be56-e34d-45a6-afbb-6031e19194e8"
  },
  {
  "pid": "15",
  "name": "Bridesmaids/Groomsmen flowers",
  "tagId": "e1b60866-1e84-4005-a284-5979e4935e54"
  },
  {
  "pid": "15",
  "name": "Standing Sprays",
  "tagId": "896d95a6-1cc8-4c88-9724-35e9ecdd527c"
  },
  {
  "pid": "10",
  "name": "Fragrant and Natural Flowers",
  "tagId": "yYpTLd3XW"
  }
  ],
  "tier2": [
  {
  "name": "Florists",
  "sysName": "florists"
  }
  ],
  "state": "active",
  "updated": "2020-08-10T16:52:45.712Z",
  "trusted": false,
  "visible": true,
  "dietary": [],
  "categoryTier1": "florists",
  "public": {
  "images": [
  {
  "id": "aodYzwFGd",
  "eid": "2b8ac67c-611e-46ac-b944-b406f2fc89c3",
  "url": "https://feast-it-web-prod.imgix.net/2b8ac67c-611e-46ac-b944-b406f2fc89c3/aodYzwFGd/Feast-It-Sweet-Pea-Rosa-Book-Now-Flowers.jpg",
  "title": ""
  },
  {
  "id": "NqRlXofLd",
  "eid": "2b8ac67c-611e-46ac-b944-b406f2fc89c3",
  "url": "https://feast-it-web-prod.imgix.net/2b8ac67c-611e-46ac-b944-b406f2fc89c3/NqRlXofLd/Feast-It-Sweet-Pea-Rosa-Book-Now.jpg",
  "title": ""
  },
  {
  "id": "lJfKQG47r6",
  "eid": "2b8ac67c-611e-46ac-b944-b406f2fc89c3",
  "url": "https://feast-it-web-prod.imgix.net/2b8ac67c-611e-46ac-b944-b406f2fc89c3/lJfKQG47r6/Feast-It-Sweet-Pea-Rosa-Book-Now-one.jpg",
  "title": ""
  },
  {
  "id": "u100WyBzw",
  "eid": "2b8ac67c-611e-46ac-b944-b406f2fc89c3",
  "url": "https://feast-it-web-prod.imgix.net/2b8ac67c-611e-46ac-b944-b406f2fc89c3/u100WyBzw/Feast-It-Sweet-Pea-Rosa-Book-Today.jpg",
  "title": ""
  },
  {
  "id": "vOOwZBcQ8",
  "eid": "2b8ac67c-611e-46ac-b944-b406f2fc89c3",
  "url": "https://feast-it-web-prod.imgix.net/2b8ac67c-611e-46ac-b944-b406f2fc89c3/vOOwZBcQ8/Feast-It-Sweet-Pea-Rosa-Event-Flowers.jpg",
  "title": ""
  },
  {
  "id": "hiTGQHh3V",
  "eid": "2b8ac67c-611e-46ac-b944-b406f2fc89c3",
  "url": "https://feast-it-web-prod.imgix.net/2b8ac67c-611e-46ac-b944-b406f2fc89c3/hiTGQHh3V/Feast_It_Sweet_Pea_Rosa_004.jpeg",
  "title": ""
  },
  {
  "id": "iMfYyoJ8yI",
  "eid": "2b8ac67c-611e-46ac-b944-b406f2fc89c3",
  "url": "https://feast-it-web-prod.imgix.net/2b8ac67c-611e-46ac-b944-b406f2fc89c3/iMfYyoJ8yI/Feast_It_Sweet_Pea_Rosa_001.jpeg",
  "title": ""
  },
  {
  "id": "QnOigrMTsd",
  "eid": "2b8ac67c-611e-46ac-b944-b406f2fc89c3",
  "url": "https://feast-it-web-prod.imgix.net/2b8ac67c-611e-46ac-b944-b406f2fc89c3/QnOigrMTsd/Feast_It_Sweet_Pea_Rosa_002.jpeg",
  "title": ""
  },
  {
  "id": "zrg0Cvxbt",
  "eid": "2b8ac67c-611e-46ac-b944-b406f2fc89c3",
  "url": "https://feast-it-web-prod.imgix.net/2b8ac67c-611e-46ac-b944-b406f2fc89c3/zrg0Cvxbt/Feast_It_Sweet_Pea_Rosa_003.jpeg",
  "title": ""
  },
  {
  "id": "azG64M1ER",
  "eid": "2b8ac67c-611e-46ac-b944-b406f2fc89c3",
  "url": "https://feast-it-web-prod.imgix.net/2b8ac67c-611e-46ac-b944-b406f2fc89c3/azG64M1ER/Feast-It-Sweet-Pea-Rosa-Wedding-Flowers-Book-Now.jpg",
  "title": ""
  },
  {
  "id": "iq7Rx5UI5",
  "eid": "2b8ac67c-611e-46ac-b944-b406f2fc89c3",
  "url": "https://feast-it-web-prod.imgix.net/2b8ac67c-611e-46ac-b944-b406f2fc89c3/iq7Rx5UI5/Feast-It-Sweet-Pea-Rosa-Book-Now-three.jpg",
  "title": ""
  },
  {
  "id": "hHZfpHZwE",
  "eid": "2b8ac67c-611e-46ac-b944-b406f2fc89c3",
  "url": "https://feast-it-web-prod.imgix.net/2b8ac67c-611e-46ac-b944-b406f2fc89c3/hHZfpHZwE/Feast-It-Sweet-Pea-Rosa-Book-Now-two.jpg",
  "title": ""
  }
  ],
  "social": [],
  "basePrice": 10,
  "video_url": "https://youtu.be/4Lxs-OkAsZo",
  "commission": 17.5,
  "description": "<p>At Sweet Pea Rosa we provide beautiful bespoke flowers for all occasions, creating romantic timeless bridal bouquets, stunning table centrepieces and show stopping focal florals. Based in Walthamstow, East London and founded by me, Sally, Sweet Pea Rosa brings to events over 7 years experience in floristry and an extreme passion for all things floral. The Sweet Pea Rosa style is free and natural, selecting floral recipes with complimenting colours and fragrance.</p><p>Whether you would like beautiful flowers for your wedding, party or any other special occasion, we will work with your theme and ideas to create something elegant and stylish that will compliment your day perfectly.&nbsp;</p>",
  "profilePicture": {
  "id": "jXB0uNyMn",
  "eid": "2b8ac67c-611e-46ac-b944-b406f2fc89c3",
  "url": "https://feast-it-web-prod.imgix.net/2b8ac67c-611e-46ac-b944-b406f2fc89c3/jXB0uNyMn/Feast-It-Sweet-Pea-Rosa-Sally-Bastard.jpg",
  "title": ""
  },
  "logistics": {
  "radius": 65000,
  "minSpend": 1000,
  "VATNumber": null,
  "setup": {
  "power": null,
  "water": null,
  "details": null
  },
  "location": {
  "lat": 51.57915,
  "long": -0.007119
  },
  "VATRegistered": false,
  "registeredName": null,
  "maxWorkingHours": 12,
  "registeredAddress": {
  "city": "London",
  "line1": "169 Grove Road",
  "line2": "Walthamstow",
  "postcode": "E17 9BZ"
  },
  "availableHours": {
  "end": "24:00",
  "start": "06:00"
  },
  "companyRegistrationNumber": null
  }
  },
  "categoryFields": {},
  "external": {
  "numReviews": "3",
  "hygieneRating": null,
  "rating": {
  "overall": "5.0",
  "quality": "5.0",
  "friendliness": "5.0",
  "valueForMoney": "5.0",
  "professionalism": "5.0"
  },
  "iZettleStaffName": null,
  "foodSafetyAgencyId": null
  },
  "algorithmDiscoverable": true
  },
  {
  "name": "Floribundi",
  "slug": "floribundi",
  "uuid": "33361f4d-aabf-4a36-b365-dbb36ea58bb2",
  "tags": [
  {
  "pid": "15",
  "name": "Bridal Bouquets",
  "tagId": "a30ee396-fd2b-4987-ae55-d0533fa3a035"
  },
  {
  "pid": "15",
  "name": "Table Arrangements",
  "tagId": "16d2be56-e34d-45a6-afbb-6031e19194e8"
  },
  {
  "pid": "15",
  "name": "Venue Arrangements",
  "tagId": "356d43b8-89ac-48e2-b171-d50736fe29a2"
  },
  {
  "pid": "15",
  "name": "Bridesmaids/Groomsmen flowers",
  "tagId": "e1b60866-1e84-4005-a284-5979e4935e54"
  },
  {
  "pid": "15",
  "name": "Floral Baskets",
  "tagId": "4780f591-15a0-44a4-97ea-052936dbae47"
  },
  {
  "pid": "15",
  "name": "Standing Sprays",
  "tagId": "896d95a6-1cc8-4c88-9724-35e9ecdd527c"
  },
  {
  "pid": "15",
  "name": "Installations",
  "tagId": "d3174ae6-410f-446a-a283-138d57a2f2fa"
  },
  {
  "pid": "15",
  "name": "Wreaths",
  "tagId": "6b40b393-7121-471e-92c7-11850792bae6"
  },
  {
  "pid": "10",
  "name": "Creative Independent Florist",
  "tagId": "DIxGtcnrK"
  }
  ],
  "tier2": [
  {
  "name": "Florists",
  "sysName": "florists"
  }
  ],
  "state": "active",
  "updated": "2020-09-15T15:32:00.380Z",
  "trusted": false,
  "visible": true,
  "dietary": [],
  "categoryTier1": "florists",
  "public": {
  "images": [
  {
  "id": "bnecYNyhL",
  "eid": "33361f4d-aabf-4a36-b365-dbb36ea58bb2",
  "url": "https://feast-it-web-prod.imgix.net/33361f4d-aabf-4a36-b365-dbb36ea58bb2/bnecYNyhL/Feast-It-Floribundi-Independent-Creative-Floristry3.jpg",
  "title": ""
  },
  {
  "id": "N78cXki5T",
  "eid": "33361f4d-aabf-4a36-b365-dbb36ea58bb2",
  "url": "https://feast-it-web-prod.imgix.net/33361f4d-aabf-4a36-b365-dbb36ea58bb2/N78cXki5T/Feast-It-Floribundi-Independent-Creative-Floristry8.jpg",
  "title": ""
  },
  {
  "id": "2v7_oEzIQh",
  "eid": "33361f4d-aabf-4a36-b365-dbb36ea58bb2",
  "url": "https://feast-it-web-prod.imgix.net/33361f4d-aabf-4a36-b365-dbb36ea58bb2/2v7_oEzIQh/Feast-It-Floribundi-Independent-Creative-Floristry9.jpg",
  "title": ""
  },
  {
  "id": "ZPgfbH_pr",
  "eid": "33361f4d-aabf-4a36-b365-dbb36ea58bb2",
  "url": "https://feast-it-web-prod.imgix.net/33361f4d-aabf-4a36-b365-dbb36ea58bb2/ZPgfbH_pr/Feast-It-Floribundi-Independent-Creative-Floristry10.jpg",
  "title": ""
  },
  {
  "id": "Qwov7pY11",
  "eid": "33361f4d-aabf-4a36-b365-dbb36ea58bb2",
  "url": "https://feast-it-web-prod.imgix.net/33361f4d-aabf-4a36-b365-dbb36ea58bb2/Qwov7pY11/Feast-It-Floribundi-Independent-Creative-Floristry12.jpg",
  "title": ""
  },
  {
  "id": "ZZMY9x2zd",
  "eid": "33361f4d-aabf-4a36-b365-dbb36ea58bb2",
  "url": "https://feast-it-web-prod.imgix.net/33361f4d-aabf-4a36-b365-dbb36ea58bb2/ZZMY9x2zd/Feast-It-Floribundi-Independent-Creative-Floristry11.jpg",
  "title": ""
  },
  {
  "id": "rlAPmgYrmd",
  "eid": "33361f4d-aabf-4a36-b365-dbb36ea58bb2",
  "url": "https://feast-it-web-prod.imgix.net/33361f4d-aabf-4a36-b365-dbb36ea58bb2/rlAPmgYrmd/Feast-It-Floribundi-Independent-Creative-Floristry1.jpg",
  "title": ""
  },
  {
  "id": "TuwDOI4fKm",
  "eid": "33361f4d-aabf-4a36-b365-dbb36ea58bb2",
  "url": "https://feast-it-web-prod.imgix.net/33361f4d-aabf-4a36-b365-dbb36ea58bb2/TuwDOI4fKm/Feast-It-Floribundi-Independent-Creative-Floristry7.jpg",
  "title": ""
  },
  {
  "id": "dGthBta3o0",
  "eid": "33361f4d-aabf-4a36-b365-dbb36ea58bb2",
  "url": "https://feast-it-web-prod.imgix.net/33361f4d-aabf-4a36-b365-dbb36ea58bb2/dGthBta3o0/Feast-It-Floribundi-Independent-Creative-Floristry6.jpg",
  "title": ""
  },
  {
  "id": "-ULGMOQHK",
  "eid": "33361f4d-aabf-4a36-b365-dbb36ea58bb2",
  "url": "https://feast-it-web-prod.imgix.net/33361f4d-aabf-4a36-b365-dbb36ea58bb2/-ULGMOQHK/Feast-It-Floribundi-Independent-Creative-Floristry4.jpg",
  "title": ""
  },
  {
  "id": "ZqElQryB8",
  "eid": "33361f4d-aabf-4a36-b365-dbb36ea58bb2",
  "url": "https://feast-it-web-prod.imgix.net/33361f4d-aabf-4a36-b365-dbb36ea58bb2/ZqElQryB8/Feast-It-Floribundi-Independent-Creative-Floristry5.jpg",
  "title": ""
  }
  ],
  "social": [],
  "basePrice": 10,
  "video_url": null,
  "commission": 17.5,
  "description": "<p>Flowers can transform a space from bland to grand and that's what the Floribundi team love most - surpassing expectations with their creations.</p><p>Floribundi are an independent florist based in South Bucks whose dedication to providing an outstanding service and quality product to each event has won them several awards, including Best Wedding Florist 2018 for South Bucks at the Global Wedding Awards. Every event the team work on is given the bespoke care and attention needed to ensure the big day fits your vision, with the team on hand to consult and use their creative expertise to curate beautiful floral arrangements with you.</p><p>With an expansive list of past clients, Floribundi have provided exceptional floristry for intimate dinners all the way through to large corporate do's and events for thousands. Whatever the event they always have the same mission: to take the brief and bring it to life in flowers - creativity is their middle name!&nbsp;</p><p>Book Floribundi for your next event on Feast It!</p>",
  "profilePicture": {
  "id": "ao5CUhlaq",
  "eid": "33361f4d-aabf-4a36-b365-dbb36ea58bb2",
  "url": "https://feast-it-web-prod.imgix.net/33361f4d-aabf-4a36-b365-dbb36ea58bb2/ao5CUhlaq/Floribundi-FeastIt.jpg",
  "title": ""
  },
  "logistics": {
  "radius": 50000,
  "minSpend": 400,
  "VATNumber": null,
  "setup": {
  "power": null,
  "water": null,
  "details": "<p><br></p>"
  },
  "location": {
  "lat": 51.608649,
  "long": -0.654284
  },
  "VATRegistered": false,
  "registeredName": null,
  "maxWorkingHours": 12,
  "registeredAddress": {
  "city": "",
  "line1": "",
  "line2": "",
  "postcode": ""
  },
  "availableHours": {
  "end": "24:00",
  "start": "06:00"
  },
  "companyRegistrationNumber": null
  }
  },
  "categoryFields": {},
  "external": {
  "numReviews": "0",
  "hygieneRating": null,
  "rating": {
  "overall": "0.0",
  "quality": null,
  "friendliness": null,
  "valueForMoney": null,
  "professionalism": null
  },
  "iZettleStaffName": null,
  "foodSafetyAgencyId": null
  },
  "algorithmDiscoverable": true
  },
  {
  "name": "Bunch London",
  "slug": "bunch-london",
  "uuid": "37651863-76b6-403e-a41b-85ab945a8bd0",
  "tags": [
  {
  "pid": "15",
  "name": "Bridal Bouquets",
  "tagId": "a30ee396-fd2b-4987-ae55-d0533fa3a035"
  },
  {
  "pid": "15",
  "name": "Bridesmaids/Groomsmen flowers",
  "tagId": "e1b60866-1e84-4005-a284-5979e4935e54"
  },
  {
  "pid": "15",
  "name": "Floral Baskets",
  "tagId": "4780f591-15a0-44a4-97ea-052936dbae47"
  },
  {
  "pid": "15",
  "name": "Venue Arrangements",
  "tagId": "356d43b8-89ac-48e2-b171-d50736fe29a2"
  },
  {
  "pid": "15",
  "name": "Installations",
  "tagId": "d3174ae6-410f-446a-a283-138d57a2f2fa"
  },
  {
  "pid": "15",
  "name": "Table Arrangements",
  "tagId": "16d2be56-e34d-45a6-afbb-6031e19194e8"
  },
  {
  "pid": "10",
  "name": "Impeccable Flowers For Every Occasion",
  "tagId": "1PJNfNgbe"
  }
  ],
  "tier2": [
  {
  "name": "Florists",
  "sysName": "florists"
  }
  ],
  "state": "active",
  "updated": "2020-08-11T15:49:12.173Z",
  "trusted": false,
  "visible": true,
  "dietary": [],
  "categoryTier1": "florists",
  "public": {
  "images": [
  {
  "id": "UPe4jEcdI",
  "eid": "37651863-76b6-403e-a41b-85ab945a8bd0",
  "url": "https://feast-it-web-prod.imgix.net/37651863-76b6-403e-a41b-85ab945a8bd0/UPe4jEcdI/Feast-It-Bunch-London-Book-Today.jpg",
  "title": ""
  },
  {
  "id": "uvyEqg9cv",
  "eid": "37651863-76b6-403e-a41b-85ab945a8bd0",
  "url": "https://feast-it-web-prod.imgix.net/37651863-76b6-403e-a41b-85ab945a8bd0/uvyEqg9cv/Feast-It-Bunch-London-Book-Now-Florists.jpg",
  "title": ""
  },
  {
  "id": "lHKQ9hxM1",
  "eid": "37651863-76b6-403e-a41b-85ab945a8bd0",
  "url": "https://feast-it-web-prod.imgix.net/37651863-76b6-403e-a41b-85ab945a8bd0/lHKQ9hxM1/Feast-It-Bunch-London-Book-Now-Wedding-Flowers.jpg",
  "title": ""
  },
  {
  "id": "_FEYOzTC8",
  "eid": "37651863-76b6-403e-a41b-85ab945a8bd0",
  "url": "https://feast-it-web-prod.imgix.net/37651863-76b6-403e-a41b-85ab945a8bd0/_FEYOzTC8/Feast-It-Bunch-London-Book-Now-Flowers.jpg",
  "title": ""
  },
  {
  "id": "z--Lyqmuc",
  "eid": "37651863-76b6-403e-a41b-85ab945a8bd0",
  "url": "https://feast-it-web-prod.imgix.net/37651863-76b6-403e-a41b-85ab945a8bd0/z--Lyqmuc/Feast-It-Bunch-London-Book-Now-Event-Flowers.jpg",
  "title": ""
  },
  {
  "id": "OTvL1lfHG",
  "eid": "37651863-76b6-403e-a41b-85ab945a8bd0",
  "url": "https://feast-it-web-prod.imgix.net/37651863-76b6-403e-a41b-85ab945a8bd0/OTvL1lfHG/Feast-It-Bunch-London-Book-Now.jpg",
  "title": ""
  }
  ],
  "social": [],
  "basePrice": 10,
  "video_url": null,
  "commission": 17.5,
  "description": "<p>Bunch London was created for a love for flowers.</p><p>After training at Scarlet and Violet and with a background in running events, Anna setup Bunch London from a Peckham studio in 2016. Long time friend and fellow florist Thomas, also with a background in production and running high end events, joined in 2017 and the duo have been creating beautiful flowers ever since.&nbsp;</p><p>Be it bouquets, workshops, events or weddings, Bunch London strives to create the perfect flower for every occasion, delivered with impeccable customer service. Our dedication and eye to detail has enabled us to work with countless wonderful couples and incredible brands including; Harrods, Van Cleef &amp; Arpels, Nyetimber, Skandium, Treatwell, LASSCO, Victor &amp; Rolf Fragrances, Debenhams, Fellowstead &amp; Dora Larsen Lingerie.&nbsp;</p><p>Bunch is here to help you express your love for those around you and as a small business we are able to give our time and expertise to each and every client. Feel free to enquire with us right here on Feast It.</p>",
  "profilePicture": {
  "id": "Z77TMDIrn",
  "eid": "37651863-76b6-403e-a41b-85ab945a8bd0",
  "url": "https://feast-it-web-prod.imgix.net/37651863-76b6-403e-a41b-85ab945a8bd0/Z77TMDIrn/Feast-It-Bunch-London-Book-Now-Flowers-Anna-and-Charlie.jpg",
  "title": ""
  },
  "logistics": {
  "radius": 40000,
  "minSpend": 400,
  "VATNumber": null,
  "setup": {
  "power": null,
  "water": null,
  "details": null
  },
  "location": {
  "lat": 51.463757,
  "long": -0.0668
  },
  "VATRegistered": false,
  "registeredName": null,
  "maxWorkingHours": 12,
  "registeredAddress": {
  "city": "London",
  "line1": "Flat 6",
  "line2": "112 Peckham rye",
  "postcode": "SE15 4HA"
  },
  "availableHours": {
  "end": "24:00",
  "start": "06:00"
  },
  "companyRegistrationNumber": null
  }
  },
  "categoryFields": {},
  "external": {
  "numReviews": "0",
  "hygieneRating": null,
  "rating": {
  "overall": "0.0",
  "quality": null,
  "friendliness": null,
  "valueForMoney": null,
  "professionalism": null
  },
  "iZettleStaffName": null,
  "foodSafetyAgencyId": null
  },
  "algorithmDiscoverable": true
  },
  {
  "name": "Me and My Bloomers",
  "slug": "me-and-my-bloomers",
  "uuid": "48f34d25-1dcf-41cb-9943-55dff0339dde",
  "tags": [
  {
  "pid": "10",
  "name": "Bespoke Floral Arrangements",
  "tagId": "eDhLVbBy3"
  }
  ],
  "tier2": [
  {
  "name": "Florists",
  "sysName": "florists"
  }
  ],
  "state": "active",
  "updated": "2020-08-06T15:42:26.907Z",
  "trusted": false,
  "visible": true,
  "dietary": [],
  "categoryTier1": "florists",
  "public": {
  "images": [
  {
  "id": "pwgMylTYpw",
  "eid": "48f34d25-1dcf-41cb-9943-55dff0339dde",
  "url": "https://feast-it-web-prod.imgix.net/48f34d25-1dcf-41cb-9943-55dff0339dde/pwgMylTYpw/Feast_it_Me_and_my_BloomersHannah___Richard_570.jpg",
  "title": ""
  },
  {
  "id": "V4r0J0Qrc",
  "eid": "48f34d25-1dcf-41cb-9943-55dff0339dde",
  "url": "https://feast-it-web-prod.imgix.net/48f34d25-1dcf-41cb-9943-55dff0339dde/V4r0J0Qrc/Feast_it_Me_and_my_BloomersIMG_0898.JPG",
  "title": ""
  },
  {
  "id": "3PqTw8F8N",
  "eid": "48f34d25-1dcf-41cb-9943-55dff0339dde",
  "url": "https://feast-it-web-prod.imgix.net/48f34d25-1dcf-41cb-9943-55dff0339dde/3PqTw8F8N/Feast_it_Me_and_my_BloomersIMG_2507.JPG",
  "title": ""
  },
  {
  "id": "5arsotr5u",
  "eid": "48f34d25-1dcf-41cb-9943-55dff0339dde",
  "url": "https://feast-it-web-prod.imgix.net/48f34d25-1dcf-41cb-9943-55dff0339dde/5arsotr5u/Feast_it_Me_and_my_BloomersHannah___Richard_751.jpg",
  "title": ""
  },
  {
  "id": "oSEM8w1rEu",
  "eid": "48f34d25-1dcf-41cb-9943-55dff0339dde",
  "url": "https://feast-it-web-prod.imgix.net/48f34d25-1dcf-41cb-9943-55dff0339dde/oSEM8w1rEu/Feast_it_Me_and_my_BloomersBD__300_of_655_.jpg",
  "title": ""
  },
  {
  "id": "UP_2li3WRr",
  "eid": "48f34d25-1dcf-41cb-9943-55dff0339dde",
  "url": "https://feast-it-web-prod.imgix.net/48f34d25-1dcf-41cb-9943-55dff0339dde/UP_2li3WRr/Feast_it_Me_and_my_Bloomersaron-klein%20index%20images-36.jpg",
  "title": ""
  },
  {
  "id": "4IrbrIedN",
  "eid": "48f34d25-1dcf-41cb-9943-55dff0339dde",
  "url": "https://feast-it-web-prod.imgix.net/48f34d25-1dcf-41cb-9943-55dff0339dde/4IrbrIedN/Feast_it_Me_and_my_BloomersIMG_2204agnesblack.jpg",
  "title": ""
  },
  {
  "id": "fykBKFcNJk",
  "eid": "48f34d25-1dcf-41cb-9943-55dff0339dde",
  "url": "https://feast-it-web-prod.imgix.net/48f34d25-1dcf-41cb-9943-55dff0339dde/fykBKFcNJk/Feast_it_Me_and_my_Bloomersaron-klein%20index%20images-7.jpg",
  "title": ""
  },
  {
  "id": "C9My2tLHbK",
  "eid": "48f34d25-1dcf-41cb-9943-55dff0339dde",
  "url": "https://feast-it-web-prod.imgix.net/48f34d25-1dcf-41cb-9943-55dff0339dde/C9My2tLHbK/Feast_it_Me_and_my_BloomersIMG_2222agnesblack.jpg",
  "title": ""
  },
  {
  "id": "Hu4PBXj6V",
  "eid": "48f34d25-1dcf-41cb-9943-55dff0339dde",
  "url": "https://feast-it-web-prod.imgix.net/48f34d25-1dcf-41cb-9943-55dff0339dde/Hu4PBXj6V/Feast_it_Me_and_my_BloomersIMG_1755.jpg",
  "title": ""
  },
  {
  "id": "-5e2utJZV",
  "eid": "48f34d25-1dcf-41cb-9943-55dff0339dde",
  "url": "https://feast-it-web-prod.imgix.net/48f34d25-1dcf-41cb-9943-55dff0339dde/-5e2utJZV/Feast_it_Me_and_my_BloomersIMG_0896.JPG",
  "title": ""
  }
  ],
  "social": [],
  "basePrice": 10,
  "video_url": null,
  "commission": 17.5,
  "description": "<p>Whether it’s a wedding, private party, supper club, press launch, or birthday, Me and My Bloomers take great delight in working with you to create and design unique flowers for your event whatever the size.</p><p>They have many years of experience working on luxury events, and promise to provide an extremely professional service. Their designs tend to be influenced by the seasons, regularly taking inspiration from the English garden and countryside, embracing a more loose and natural style.</p><p>Drawing from their backgrounds in fine art, set design and event coordination, Me and My Bloomers have the ability to see your whole event, ensuring the floral design compliments every detail you have planned for your special day.</p>",
  "profilePicture": {
  "id": "dge8p4741",
  "eid": "48f34d25-1dcf-41cb-9943-55dff0339dde",
  "url": "https://feast-it-web-prod.imgix.net/48f34d25-1dcf-41cb-9943-55dff0339dde/dge8p4741/Feast_it_Me_and_my_BloomersIMG_1708.JPG",
  "title": ""
  },
  "logistics": {
  "radius": 300000,
  "minSpend": 1500,
  "VATNumber": null,
  "setup": {
  "power": null,
  "water": null,
  "details": null
  },
  "location": {
  "lat": 52.132609,
  "long": -0.9875
  },
  "VATRegistered": false,
  "registeredName": null,
  "maxWorkingHours": 10,
  "registeredAddress": {
  "city": "",
  "line1": "",
  "line2": "",
  "postcode": "NN12 6YY"
  },
  "availableHours": {
  "end": "24:00",
  "start": "06:00"
  },
  "companyRegistrationNumber": null
  }
  },
  "categoryFields": {},
  "external": {
  "numReviews": "0",
  "hygieneRating": null,
  "rating": {
  "overall": "0.0",
  "quality": null,
  "friendliness": null,
  "valueForMoney": null,
  "professionalism": null
  },
  "iZettleStaffName": null,
  "foodSafetyAgencyId": null
  },
  "algorithmDiscoverable": false
  },
  {
  "name": "Sunflowers Florist",
  "slug": "sunflowers-florist",
  "uuid": "5b80f7e3-acd7-41c3-897b-54ec82535d68",
  "tags": [
  {
  "pid": "10",
  "name": "Featured on The Big Flower Fight",
  "tagId": "_tkSUqUph"
  }
  ],
  "tier2": [
  {
  "name": "Florists",
  "sysName": "florists"
  }
  ],
  "state": "active",
  "updated": "2020-09-02T11:18:52.463Z",
  "trusted": false,
  "visible": true,
  "dietary": [],
  "categoryTier1": "florists",
  "public": {
  "images": [
  {
  "id": "cb-Mhd0IN",
  "eid": "5b80f7e3-acd7-41c3-897b-54ec82535d68",
  "url": "https://feast-it-web-prod.imgix.net/5b80f7e3-acd7-41c3-897b-54ec82535d68/cb-Mhd0IN/Feast_It_%20Sun_Florist.Screen%20Shot%202020-07-03%20at%2011.51.58.png",
  "title": ""
  },
  {
  "id": "3-gs-_mlW",
  "eid": "5b80f7e3-acd7-41c3-897b-54ec82535d68",
  "url": "https://feast-it-web-prod.imgix.net/5b80f7e3-acd7-41c3-897b-54ec82535d68/3-gs-_mlW/Feast_It_%20Sun_Florist.Screen%20Shot%202020-07-03%20at%2012.02.53.png",
  "title": ""
  },
  {
  "id": "-Y2ksIXy6H",
  "eid": "5b80f7e3-acd7-41c3-897b-54ec82535d68",
  "url": "https://feast-it-web-prod.imgix.net/5b80f7e3-acd7-41c3-897b-54ec82535d68/-Y2ksIXy6H/Feast_It_%20Sun_Florist.Screen%20Shot%202020-07-03%20at%2012.04.31.png",
  "title": ""
  },
  {
  "id": "fz2lLkO6C",
  "eid": "5b80f7e3-acd7-41c3-897b-54ec82535d68",
  "url": "https://feast-it-web-prod.imgix.net/5b80f7e3-acd7-41c3-897b-54ec82535d68/fz2lLkO6C/Feast_It_%20Sun_Florist.Screen%20Shot%202020-07-03%20at%2012.03.22.png",
  "title": ""
  },
  {
  "id": "m5gMOXUAV",
  "eid": "5b80f7e3-acd7-41c3-897b-54ec82535d68",
  "url": "https://feast-it-web-prod.imgix.net/5b80f7e3-acd7-41c3-897b-54ec82535d68/m5gMOXUAV/Feast_It_%20Sun_Florist.Screen%20Shot%202020-07-03%20at%2011.52.51.png",
  "title": ""
  },
  {
  "id": "xEy3Emmp9",
  "eid": "5b80f7e3-acd7-41c3-897b-54ec82535d68",
  "url": "https://feast-it-web-prod.imgix.net/5b80f7e3-acd7-41c3-897b-54ec82535d68/xEy3Emmp9/Feast_It_%20Sun_Florist.Screen%20Shot%202020-07-03%20at%2011.49.46.png",
  "title": ""
  },
  {
  "id": "zNYcQO5aO",
  "eid": "5b80f7e3-acd7-41c3-897b-54ec82535d68",
  "url": "https://feast-it-web-prod.imgix.net/5b80f7e3-acd7-41c3-897b-54ec82535d68/zNYcQO5aO/Feast_It_%20Sun_Florist.Screen%20Shot%202020-07-03%20at%2011.52.30.png",
  "title": ""
  },
  {
  "id": "dmluxoxPIy",
  "eid": "5b80f7e3-acd7-41c3-897b-54ec82535d68",
  "url": "https://feast-it-web-prod.imgix.net/5b80f7e3-acd7-41c3-897b-54ec82535d68/dmluxoxPIy/Feast_It_%20Sun_Florist.Screen%20Shot%202020-07-03%20at%2011.52.15.png",
  "title": ""
  },
  {
  "id": "nmARMK72r",
  "eid": "5b80f7e3-acd7-41c3-897b-54ec82535d68",
  "url": "https://feast-it-web-prod.imgix.net/5b80f7e3-acd7-41c3-897b-54ec82535d68/nmARMK72r/Feast_It_%20Sun_Florist59478695_8C7F_47A3_8E0A_E2B70A04CBB0.jpeg",
  "title": ""
  },
  {
  "id": "uuf5ZuNnmI",
  "eid": "5b80f7e3-acd7-41c3-897b-54ec82535d68",
  "url": "https://feast-it-web-prod.imgix.net/5b80f7e3-acd7-41c3-897b-54ec82535d68/uuf5ZuNnmI/Feast_It_%20Sun_Florist3FA81285_ECF6_40A9_BAB5_057111DC5DA0.jpeg",
  "title": ""
  },
  {
  "id": "XhLSAgXzH",
  "eid": "5b80f7e3-acd7-41c3-897b-54ec82535d68",
  "url": "https://feast-it-web-prod.imgix.net/5b80f7e3-acd7-41c3-897b-54ec82535d68/XhLSAgXzH/Feast_It_%20Sun_Florist27EEA187_2B37_43DB_B01B_4F0F62C3C7A2.jpeg",
  "title": ""
  },
  {
  "id": "Ar_5UEMTT",
  "eid": "5b80f7e3-acd7-41c3-897b-54ec82535d68",
  "url": "https://feast-it-web-prod.imgix.net/5b80f7e3-acd7-41c3-897b-54ec82535d68/Ar_5UEMTT/Feast_It_%20Sun_Florist.Screen%20Shot%202020-07-03%20at%2012.05.03.png",
  "title": ""
  },
  {
  "id": "XJ1e_mS9I4",
  "eid": "5b80f7e3-acd7-41c3-897b-54ec82535d68",
  "url": "https://feast-it-web-prod.imgix.net/5b80f7e3-acd7-41c3-897b-54ec82535d68/XJ1e_mS9I4/Feast_It_%20Sun_Florist006B0398_05F4_4E97_97FD_54F42C0E14C4.jpeg",
  "title": ""
  }
  ],
  "social": [],
  "basePrice": 10,
  "video_url": null,
  "commission": 17.5,
  "description": "<p>London-based Sunflowers Florist is run by the talented and passionate Raymond, star of Netflix series The Big Flower Fight. With 13 years experience under his belt in weddings, corporate and hotel floral designs, it’s no wonder Raymond won the ‘Best in Bloom’ title on episode 2 of the show!</p><p>For your wedding, Raymond and the Sunflowers Florist team can create breathtaking table centrepieces, flower arches, ceiling and stair installations as well as stunning bouquets and boutonnieres for the perfect final touch to the bridal party. Never settling for prepackaged floral arrangements, Raymond will create your floral designs from scratch to match your specific theme or Pinterest inspiration!</p><p>Looking to decorate your private or corporate party? There’s nothing Raymond can’t create from flowers and plants, including unique topiary designs from plants and moss in the shapes of animals - imagine that as a talking piece!</p>",
  "profilePicture": {
  "id": "uguH9I6ec",
  "eid": "5b80f7e3-acd7-41c3-897b-54ec82535d68",
  "url": "https://feast-it-web-prod.imgix.net/5b80f7e3-acd7-41c3-897b-54ec82535d68/uguH9I6ec/Feast_It_%20Sun_Florist.Screen%20Shot%202020-07-03%20at%2011.46.56.png",
  "title": ""
  },
  "logistics": {
  "radius": 50000,
  "minSpend": 500,
  "VATNumber": null,
  "setup": {
  "power": null,
  "water": null,
  "details": "<p><br></p>"
  },
  "location": {
  "lat": 51.434146,
  "long": -0.017364
  },
  "VATRegistered": false,
  "registeredName": null,
  "maxWorkingHours": 12,
  "registeredAddress": {
  "city": "London",
  "line1": "233 Bromley Road",
  "line2": "Catford",
  "postcode": "SE6 2PG"
  },
  "availableHours": {
  "end": "22:00",
  "start": "06:00"
  },
  "companyRegistrationNumber": null
  }
  },
  "categoryFields": {},
  "external": {
  "numReviews": "3",
  "hygieneRating": null,
  "rating": {
  "overall": "5.0",
  "quality": "5.0",
  "friendliness": "5.0",
  "valueForMoney": "5.0",
  "professionalism": "5.0"
  },
  "iZettleStaffName": null,
  "foodSafetyAgencyId": null
  },
  "algorithmDiscoverable": true
  },
  {
  "name": "Sarah Maylin Flowers",
  "slug": "sarah-maylin-flowers",
  "uuid": "64e10c6c-b4b0-4fa6-969a-8d505bbedeab",
  "tags": [
  {
  "pid": "10",
  "name": "Florist With A Distinct Style",
  "tagId": "7sVxl1GNV"
  }
  ],
  "tier2": [
  {
  "name": "Florists",
  "sysName": "florists"
  }
  ],
  "state": "active",
  "updated": "2020-08-12T11:21:12.049Z",
  "trusted": false,
  "visible": true,
  "dietary": [],
  "categoryTier1": "florists",
  "public": {
  "images": [
  {
  "id": "tnVws8A3QF",
  "eid": "64e10c6c-b4b0-4fa6-969a-8d505bbedeab",
  "url": "https://feast-it-web-prod.imgix.net/64e10c6c-b4b0-4fa6-969a-8d505bbedeab/tnVws8A3QF/E649F817_9C79_44A5_87C4_411BCCA79593.jpeg",
  "title": ""
  },
  {
  "id": "KqF6nYL205",
  "eid": "64e10c6c-b4b0-4fa6-969a-8d505bbedeab",
  "url": "https://feast-it-web-prod.imgix.net/64e10c6c-b4b0-4fa6-969a-8d505bbedeab/KqF6nYL205/9ADC9261_9E46_49C7_B962_CAD378C7C3A0.jpeg",
  "title": ""
  },
  {
  "id": "2H8x4OFxS6",
  "eid": "64e10c6c-b4b0-4fa6-969a-8d505bbedeab",
  "url": "https://feast-it-web-prod.imgix.net/64e10c6c-b4b0-4fa6-969a-8d505bbedeab/2H8x4OFxS6/75C74555_86C5_482E_BA2D_027F57C61E37.jpeg",
  "title": ""
  },
  {
  "id": "0esR01xC0I",
  "eid": "64e10c6c-b4b0-4fa6-969a-8d505bbedeab",
  "url": "https://feast-it-web-prod.imgix.net/64e10c6c-b4b0-4fa6-969a-8d505bbedeab/0esR01xC0I/BFD71A99_DD4C_40D5_B129_2D0538A4A02E.jpeg",
  "title": ""
  },
  {
  "id": "77sOnhIbi",
  "eid": "64e10c6c-b4b0-4fa6-969a-8d505bbedeab",
  "url": "https://feast-it-web-prod.imgix.net/64e10c6c-b4b0-4fa6-969a-8d505bbedeab/77sOnhIbi/F7B1A9BB_F074_440A_9AEF_37DD9C6EB2B6.jpeg",
  "title": ""
  },
  {
  "id": "ETOZal-Q_",
  "eid": "64e10c6c-b4b0-4fa6-969a-8d505bbedeab",
  "url": "https://feast-it-web-prod.imgix.net/64e10c6c-b4b0-4fa6-969a-8d505bbedeab/ETOZal-Q_/DB3D4299_D148_47A4_9744_4E1154478D34.jpeg",
  "title": ""
  }
  ],
  "social": [],
  "basePrice": 10,
  "video_url": null,
  "commission": 17.5,
  "description": "<p>Sarah fell in love with flowers and studied floristry in New Zealand. She now has oodles of experience in designing truly beautiful floral creations. Her distinct styles of floristry will reflect and enhance the feel of your day, in exactly the way you want it to be remembered.</p><p>From wedding buttonholes to bridal bouquets, church flowers to table decorations, sophisticated style to colour explosions, Sarah can do it all. Although she specialises in weddings, Sarah also creates stunning floral displays for funerals, private parties and corporate events.&nbsp;</p><p>Based in Hitchin, Sarah is perfectly situated for events in Hertfordshire, London and beyond and looks forward to hearing more about your event!&nbsp;</p>",
  "profilePicture": {
  "id": "M6lnY_YU1",
  "eid": "64e10c6c-b4b0-4fa6-969a-8d505bbedeab",
  "url": "https://feast-it-web-prod.imgix.net/64e10c6c-b4b0-4fa6-969a-8d505bbedeab/M6lnY_YU1/A28387C1_33FA_4FE4_990B_486C61FF1470.jpeg",
  "title": ""
  },
  "logistics": {
  "radius": 100000,
  "minSpend": 500,
  "VATNumber": null,
  "setup": {
  "power": null,
  "water": null,
  "details": null
  },
  "location": {
  "lat": 51.937133,
  "long": -0.272286
  },
  "VATRegistered": false,
  "registeredName": null,
  "maxWorkingHours": 12,
  "registeredAddress": {
  "city": "Hitchin",
  "line1": "10 Newlands Lane",
  "line2": "",
  "postcode": "SG4 9AY"
  },
  "availableHours": {
  "end": "24:00",
  "start": "06:00"
  },
  "companyRegistrationNumber": null
  }
  },
  "categoryFields": {},
  "external": {
  "numReviews": "0",
  "hygieneRating": null,
  "rating": {
  "overall": "0.0",
  "quality": null,
  "friendliness": null,
  "valueForMoney": null,
  "professionalism": null
  },
  "iZettleStaffName": null,
  "foodSafetyAgencyId": null
  },
  "algorithmDiscoverable": true
  }
  ],
  "numPages": 3,
  "count": 23
  }